cutecharts/__init__.py
cutecharts/_version.py
cutecharts/faker.py
cutecharts/globals.py
cutecharts/charts/__init__.py
cutecharts/charts/bar.py
cutecharts/charts/basic.py
cutecharts/charts/line.py
cutecharts/charts/pie.py
cutecharts/charts/radar.py
cutecharts/charts/scatter.py
cutecharts/components/__init__.py
cutecharts/components/page.py
cutecharts/render/__init__.py
cutecharts/render/engine.py
cutecharts/render/templates/basic_jupyter_lab.html
cutecharts/render/templates/basic_jupyter_notebook.html
cutecharts/render/templates/basic_local.html
cutecharts/render/templates/macro
cutecharts/render/templates/page_jupyter_lab.html
cutecharts/render/templates/page_jupyter_notebook.html
cutecharts/render/templates/page_local.html
example/__init__.py
example/example_bar.py
example/example_line.py
example/example_page.py
example/example_pie.py
example/example_radar.py
example/example_scatter.py
cutecharts-1.1.0.dist-info/LICENSE
cutecharts-1.1.0.dist-info/METADATA
cutecharts-1.1.0.dist-info/WHEEL
cutecharts-1.1.0.dist-info/top_level.txt
cutecharts-1.1.0.dist-info/RECORD
