Metadata-Version: 2.1
Name: cutecharts
Version: 1.1.0
Summary: Hand drawing style charts library for Python.
Home-page: https://github.com/chenjiandongx/cutecharts
Author: chenjiandongx
Author-email: chenjiandongx@qq.com
License: MIT
Keywords: cute,charts,plotting-tool
Platform: UNKNOWN
Classifier: Development Status :: 4 - Beta
Classifier: Environment :: Console
Classifier: Intended Audience :: Developers
Classifier: License :: OSI Approved :: MIT License
Classifier: Operating System :: OS Independent
Classifier: Programming Language :: Python
Classifier: Programming Language :: Python :: 3.6
Classifier: Programming Language :: Python :: 3.7
Classifier: Topic :: Software Development :: Libraries
Requires-Dist: jinja2
